databricks_warehouse/__init__.py
databricks_warehouse/sql_connect.py
databricks_warehouse-1.0.0.dist-info/METADATA
databricks_warehouse-1.0.0.dist-info/WHEEL
databricks_warehouse-1.0.0.dist-info/RECORD
