Metadata-Version: 2.1
Name: databricks_warehouse
Version: 1.0.0
Summary: A library that wraps the databricks-sql-connector for running queries on Databricks
Author: Thomas Richards
Author-email: thomas.c.richards@outlook.com
Requires-Python: >=3.9,<4.0
Classifier: Programming Language :: Python :: 3
Classifier: Programming Language :: Python :: 3.9
Classifier: Programming Language :: Python :: 3.10
Classifier: Programming Language :: Python :: 3.11
Classifier: Programming Language :: Python :: 3.12
Provides-Extra: connect
Requires-Dist: databricks-sdk (>=0.36.0,<0.37.0)
Requires-Dist: databricks-sql-connector[pyarrow] (>=2.9)
Requires-Dist: polars (>=1,<2)
Requires-Dist: pytest-mock (>=3.14.1,<4.0.0)
Requires-Dist: toml (>=0,<1)
